Ej2/Ej2.v
module BUF3(input wire ENABLE, input wire [3:0]INPUT, output wire [3:0]Y1);
	assign Y1 = ENABLE ? INPUT : 4'bz;
endmodule

module ALU (input wire [3:0]A, input wire [3:0]B, input wire [2:0]SELECTION, output reg [3:0]Y, output reg MJM, output reg CARGAR); 
reg [4:0]X;

	always @ (A or B or SELECTION) 
		case (SELECTION) 
			0 : begin
				Y = A;
				MJM = ~Y[0]&~Y[1]&~Y[2]&~Y[3];
				end
			1 : begin
				X = A - B; 
				Y[0] = X[0];
				Y[1] = X[1];
				Y[2] = X[2];
				Y[3] = X[3];
				CARGAR = X[4];
				MJM = ~Y[0]&~Y[1]&~Y[2]&~Y[3];
				end 
			2 : begin
				Y = B;
				MJM = ~Y[0]&~Y[1]&~Y[2]&~Y[3];
				end
			3 : begin
				X = A + B; 
				Y[0] = X[0];
				Y[1] = X[1];
				Y[2] = X[2];
				Y[3] = X[3];
				CARGAR = X[4];
				MJM = ~Y[0]&~Y[1]&~Y[2]&~Y[3];
				end
			4 : begin
				Y = ~(A&B);
				MJM = ~Y[0]&~Y[1]&~Y[2]&~Y[3];
				end
			default : $display("ERROR EN LA SELECCIÓN"); 
		endcase 
endmodule

module ACC(input wire CLOCK, input wire [3:0]FD, input wire RESET, input wire ENABLE, output [3:0]Q0);
reg Q0;
	always @(posedge CLOCK or	posedge RESET or posedge ENABLE)
		if (RESET)begin
		Q0 <= 0;
	end else if(ENABLE) begin
		Q0 <= FD;
	end
endmodule

module Eje2(input wire CLOCK, RESET, EN1, EN2, EN3, input wire [3:0]INPUT, input wire [2:0]SELECTION, output wire [3:0]Y, output wire MJM, CARGAR);
	wire [3:0]YBuf1;
	wire [3:0]YACC;
	wire [3:0]YALU;
	BUF3 O1(EN1, INPUT, YBuf1);
	ACC O3(CLOCK, YALU, RESET, EN3, YACC);
	ALU O2(YACC, YBuf1, SELECTION, YALU, MJM, CARGAR);
	BUF3 O4(EN2, YALU, Y);
endmodule

Ej2/Ej2_tb.v
module Ej2();

  reg CLOCK, EN1, EN2, EN3, RESET; reg [3:0]INPUT; reg [2:0]SELECTION;
  wire [3:0]Y; wire MJM, CARGAR;

	Eje2 U1(CLOCK, RESET, EN1, EN2, EN3, INPUT, SELECTION, Y, MJM, CARGAR);


initial begin
	CLOCK=0;
	forever #5 CLOCK = ~CLOCK;
end
  initial begin
	#3
	$display("         EJ2\n");
    $display("CLK R E1 E2 E3  INPUT   Sel | Y   MJM CARGAR");
    $display("-------------------------------------------");
    $monitor("%b   %b %b  %b  %b  %b  %b | %b  %b    %b", CLOCK, RESET, EN1, EN2, EN3, INPUT, SELECTION, Y, MJM, CARGAR);
       RESET = 1; EN1 = 0; EN2 = 0; EN3 = 0; INPUT = 0; SELECTION = 0;
	   #10 RESET = 0; EN1 = 1; EN2 = 1; EN3 = 1;
	   #10 INPUT = 1;
	   #10 INPUT = 2;
	   #10 INPUT = 3;
	   #10 INPUT = 10;
	   #10 SELECTION = 2;
	   #10 INPUT = 10;
	   #10 SELECTION = 1; INPUT = 5;
	   #10 SELECTION = 3;
	   #20 SELECTION = 4;   
  end


	initial
    #130 $finish;
  initial begin
    $dumpfile("Ej2_tb.vcd");
    $dumpvars(0, Ej2);
  end
endmodule

Ej2/Ej2_tb.vcd
$date
	Sat Nov 07 00:06:20 2020
$end
$version
	Icarus Verilog
$end
$timescale
	1ps
$end
$scope module Ej2 $end
$var wire 4 ! Y [3:0] $end
$var wire 1 " MJM $end
$var wire 1 # CARGAR $end
$var reg 1 $ CLOCK $end
$var reg 1 % EN1 $end
$var reg 1 & EN2 $end
$var reg 1 ' EN3 $end
$var reg 4 ( INPUT [3:0] $end
$var reg 1 ) RESET $end
$var reg 3 * SELECTION [2:0] $end
$scope module U1 $end
$var wire 1 $ CLOCK $end
$var wire 1 % EN1 $end
$var wire 1 & EN2 $end
$var wire 1 ' EN3 $end
$var wire 4 + INPUT [3:0] $end
$var wire 1 ) RESET $end
$var wire 3 , SELECTION [2:0] $end
$var wire 4 - YBuf1 [3:0] $end
$var wire 4 . YALU [3:0] $end
$var wire 4 / YACC [3:0] $end
$var wire 4 0 Y [3:0] $end
$var wire 1 " MJM $end
$var wire 1 # CARGAR $end
$scope module O1 $end
$var wire 1 % ENABLE $end
$var wire 4 1 INPUT [3:0] $end
$var wire 4 2 Y1 [3:0] $end
$upscope $end
$scope module O2 $end
$var wire 4 3 B [3:0] $end
$var wire 3 4 SELECTION [2:0] $end
$var wire 4 5 A [3:0] $end
$var reg 1 # CARGAR $end
$var reg 1 " MJM $end
$var reg 5 6 X [4:0] $end
$var reg 4 7 Y [3:0] $end
$upscope $end
$scope module O3 $end
$var wire 1 $ CLOCK $end
$var wire 1 ' ENABLE $end
$var wire 4 8 FD [3:0] $end
$var wire 1 ) RESET $end
$var reg 4 9 Q0 [3:0] $end
$upscope $end
$scope module O4 $end
$var wire 1 & ENABLE $end
$var wire 4 : INPUT [3:0] $end
$var wire 4 ; Y1 [3:0] $end
$upscope $end
$upscope $end
$upscope $end
$enddefinitions $end
#0
$dumpvars
bx ;
bx :
bx 9
bx 8
bx 7
bx 6
bx 5
bx 4
bx 3
bx 2
bx 1
bx 0
bx /
bx .
bx -
bx ,
bx +
bx *
x)
bx (
x'
x&
x%
0$
x#
x"
bx !
$end
#3
1"
b0 .
b0 7
b0 8
b0 :
b0 /
b0 5
b0 9
bz !
bz 0
bz ;
bz -
bz 2
bz 3
b0 *
b0 ,
b0 4
b0 (
b0 +
b0 1
0'
0&
0%
1)
#5
1$
#10
0$
#13
b0 !
b0 0
b0 ;
b0 -
b0 2
b0 3
1'
1&
1%
0)
#15
1$
#20
0$
#23
b1 -
b1 2
b1 3
b1 (
b1 +
b1 1
#25
1$
#30
0$
#33
b10 -
b10 2
b10 3
b10 (
b10 +
b10 1
#35
1$
#40
0$
#43
b11 -
b11 2
b11 3
b11 (
b11 +
b11 1
#45
1$
#50
0$
#53
b1010 -
b1010 2
b1010 3
b1010 (
b1010 +
b1010 1
#55
1$
#60
0$
#63
b1010 !
b1010 0
b1010 ;
0"
b1010 .
b1010 7
b1010 8
b1010 :
b10 *
b10 ,
b10 4
#65
b1010 /
b1010 5
b1010 9
1$
#70
0$
#75
1$
#80
0$
#83
b101 !
b101 0
b101 ;
b101 -
b101 2
b101 3
0"
0#
b101 .
b101 7
b101 8
b101 :
b101 6
b101 (
b101 +
b101 1
b1 *
b1 ,
b1 4
#85
b0 !
b0 0
b0 ;
1"
b0 .
b0 7
b0 8
b0 :
b0 6
b101 /
b101 5
b101 9
1$
#90
0$
#93
b1010 !
b1010 0
b1010 ;
0"
b1010 .
b1010 7
b1010 8
b1010 :
b1010 6
b11 *
b11 ,
b11 4
#95
b1111 !
b1111 0
b1111 ;
b1111 .
b1111 7
b1111 8
b1111 :
b1111 6
b1010 /
b1010 5
b1010 9
1$
#100
0$
#105
b100 !
b100 0
b100 ;
1#
b100 .
b100 7
b100 8
b100 :
b10100 6
b1111 /
b1111 5
b1111 9
1$
#110
0$
#113
b1010 !
b1010 0
b1010 ;
b1010 .
b1010 7
b1010 8
b1010 :
b100 *
b100 ,
b100 4
#115
b1111 !
b1111 0
b1111 ;
b1111 .
b1111 7
b1111 8
b1111 :
b1010 /
b1010 5
b1010 9
1$
#120
0$
#125
b1010 !
b1010 0
b1010 ;
b1010 .
b1010 7
b1010 8
b1010 :
b1111 /
b1111 5
b1111 9
1$
